[{"Version":"1.1","TranDtls":{"TaxSch":"GST","SupTyp":"B2B","IgstOnIntra":"N","RegRev":"N","EcmGstin":null},"DocDtls":{"Typ":"INV","No":"TAX22301230","Dt":"02\/07\/2022"},"SellerDtls":{"Gstin":"09AAMFC6710F2ZG","LglNm":"CRAZY BAKERY UDYOG","TrdNm":"CRAZY BAKERY UDYOG","Addr1":"PLOT NO. G-3A, SECTOR-15, GIDA, Sahjanwa Road, Gorakhpur","Addr2":null,"Loc":"Gorakhpur","Pin":273209,"Stcd":"09","Ph":"9838755227"},"BuyerDtls":{"Gstin":"09AZBPG0900H1ZW","LglNm":"SHREE MAA VINDHYAVASHNI TRADERS","TrdNm":"SHREE MAA VINDHYAVASHNI TRADERS","Pos":"9","Addr1":"PAWAI ROAD,NEAR UBI","Addr2":null,"Loc":"JAUNPUR","Pin":223225,"Stcd":"9","Ph":null},"DispDtls":{"Nm":"SHREE MAA VINDHYAVASHNI TRADERS","Addr1":"PAWAI ROAD,NEAR UBI","Addr2":null,"Loc":"JAUNPUR","Pin":223225,"Stcd":"9"},"ShipDtls":{"Gstin":"09AZBPG0900H1ZW","LglNm":"SHREE MAA VINDHYAVASHNI TRADERS","TrdNm":"SHREE MAA VINDHYAVASHNI TRADERS","Addr1":"PAWAI ROAD,NEAR UBI","Addr2":null,"Loc":"JAUNPUR","Pin":223225,"Stcd":"9"},"ValDtls":{"AssVal":167591.04,"IgstVal":0,"CgstVal":4189.78,"SgstVal":4189.78,"CesVal":0,"StCesVal":0,"Discount":0,"OthChrg":175.97,"RndOffAmt":0.44,"TotInvVal":176147},"ExpDtls":{"ShipBNo":null,"ShipBDt":null,"Port":null,"RefClm":null,"ForCur":null,"CntCode":null,"ExpDuty":0},"EwbDtls":null,"ItemList":[{"SlNo":"1","PrdDesc":"210690","IsServc":"N","HsnCd":"210690","Barcde":null,"Qty":4500,"FreeQty":0,"Unit":"Pcs","UnitPrice":1.38,"TotAmt":6210,"Discount":0,"PreTaxVal":0,"AssAmt":6210,"GstRt":5,"IgstAmt":0,"CgstAmt":155.25,"SgstAmt":155.25,"CesRt":0,"CesAmt":0,"CesNonAdvlAmt":0,"StateCesRt":0,"StateCesAmt":0,"StateCesNonAdvlAmt":0,"OthChrg":0,"TotItemVal":6520.5,"BchDtls":null},{"SlNo":"2","PrdDesc":"210690","IsServc":"N","HsnCd":"210690","Barcde":null,"Qty":15000,"FreeQty":0,"Unit":"Pcs","UnitPrice":1.38,"TotAmt":20700,"Discount":0,"PreTaxVal":0,"AssAmt":20700,"GstRt":5,"IgstAmt":0,"CgstAmt":517.5,"SgstAmt":517.5,"CesRt":0,"CesAmt":0,"CesNonAdvlAmt":0,"StateCesRt":0,"StateCesAmt":0,"StateCesNonAdvlAmt":0,"OthChrg":0,"TotItemVal":21735,"BchDtls":null},{"SlNo":"3","PrdDesc":"210690","IsServc":"N","HsnCd":"210690","Barcde":null,"Qty":14400,"FreeQty":0,"Unit":"Pcs","UnitPrice":3.52,"TotAmt":50688,"Discount":0,"PreTaxVal":0,"AssAmt":50688,"GstRt":5,"IgstAmt":0,"CgstAmt":1267.2,"SgstAmt":1267.2,"CesRt":0,"CesAmt":0,"CesNonAdvlAmt":0,"StateCesRt":0,"StateCesAmt":0,"StateCesNonAdvlAmt":0,"OthChrg":0,"TotItemVal":53222.4,"BchDtls":null},{"SlNo":"4","PrdDesc":"210690","IsServc":"N","HsnCd":"210690","Barcde":null,"Qty":7500,"FreeQty":0,"Unit":"Pcs","UnitPrice":1.38,"TotAmt":10350,"Discount":0,"PreTaxVal":0,"AssAmt":10350,"GstRt":5,"IgstAmt":0,"CgstAmt":258.75,"SgstAmt":258.75,"CesRt":0,"CesAmt":0,"CesNonAdvlAmt":0,"StateCesRt":0,"StateCesAmt":0,"StateCesNonAdvlAmt":0,"OthChrg":0,"TotItemVal":10867.5,"BchDtls":null},{"SlNo":"5","PrdDesc":"210690","IsServc":"N","HsnCd":"210690","Barcde":null,"Qty":7200,"FreeQty":0,"Unit":"Pcs","UnitPrice":3.09,"TotAmt":22248,"Discount":0,"PreTaxVal":0,"AssAmt":22248,"GstRt":5,"IgstAmt":0,"CgstAmt":556.2,"SgstAmt":556.2,"CesRt":0,"CesAmt":0,"CesNonAdvlAmt":0,"StateCesRt":0,"StateCesAmt":0,"StateCesNonAdvlAmt":0,"OthChrg":0,"TotItemVal":23360.4,"BchDtls":null},{"SlNo":"6","PrdDesc":"210690","IsServc":"N","HsnCd":"210690","Barcde":null,"Qty":2400,"FreeQty":0,"Unit":"Pcs","UnitPrice":3.09,"TotAmt":7416,"Discount":0,"PreTaxVal":0,"AssAmt":7416,"GstRt":5,"IgstAmt":0,"CgstAmt":185.4,"SgstAmt":185.4,"CesRt":0,"CesAmt":0,"CesNonAdvlAmt":0,"StateCesRt":0,"StateCesAmt":0,"StateCesNonAdvlAmt":0,"OthChrg":0,"TotItemVal":7786.8,"BchDtls":null},{"SlNo":"7","PrdDesc":"210690","IsServc":"N","HsnCd":"210690","Barcde":null,"Qty":3600,"FreeQty":0,"Unit":"Pcs","UnitPrice":3.09,"TotAmt":11124,"Discount":0,"PreTaxVal":0,"AssAmt":11124,"GstRt":5,"IgstAmt":0,"CgstAmt":278.1,"SgstAmt":278.1,"CesRt":0,"CesAmt":0,"CesNonAdvlAmt":0,"StateCesRt":0,"StateCesAmt":0,"StateCesNonAdvlAmt":0,"OthChrg":0,"TotItemVal":11680.2,"BchDtls":null},{"SlNo":"8","PrdDesc":"210690","IsServc":"N","HsnCd":"210690","Barcde":null,"Qty":5760,"FreeQty":0,"Unit":"Pcs","UnitPrice":3.43,"TotAmt":19756.8,"Discount":0,"PreTaxVal":0,"AssAmt":19756.8,"GstRt":5,"IgstAmt":0,"CgstAmt":493.92,"SgstAmt":493.92,"CesRt":0,"CesAmt":0,"CesNonAdvlAmt":0,"StateCesRt":0,"StateCesAmt":0,"StateCesNonAdvlAmt":0,"OthChrg":0,"TotItemVal":20744.64,"BchDtls":null},{"SlNo":"9","PrdDesc":"210690","IsServc":"N","HsnCd":"210690","Barcde":null,"Qty":5568,"FreeQty":0,"Unit":"Pcs","UnitPrice":3.43,"TotAmt":19098.24,"Discount":0,"PreTaxVal":0,"AssAmt":19098.24,"GstRt":5,"IgstAmt":0,"CgstAmt":477.46,"SgstAmt":477.46,"CesRt":0,"CesAmt":0,"CesNonAdvlAmt":0,"StateCesRt":0,"StateCesAmt":0,"StateCesNonAdvlAmt":0,"OthChrg":0,"TotItemVal":20053.15,"BchDtls":null}]}]