[{"Version":"1.1","TranDtls":{"TaxSch":"GST","SupTyp":"B2B","IgstOnIntra":"N","RegRev":"N","EcmGstin":null},"DocDtls":{"Typ":"INV","No":"TAX22301499","Dt":"27\/07\/2022"},"SellerDtls":{"Gstin":"09AAMFC6710F2ZG","LglNm":"CRAZY BAKERY UDYOG","TrdNm":"CRAZY BAKERY UDYOG","Addr1":"PLOT NO. G-3A, SECTOR-15, GIDA, Sahjanwa Road, Gorakhpur","Addr2":null,"Loc":"Gorakhpur","Pin":273209,"Stcd":"09","Ph":"9838755227"},"BuyerDtls":{"Gstin":"10CIJPB7595N1ZW","LglNm":"RAJA ENTERPRISES","TrdNm":"RAJA ENTERPRISES","Pos":"10","Addr1":"KHUSKIBAGH, KAPTANPARA","Addr2":null,"Loc":"PURNIA","Pin":854305,"Stcd":"10","Ph":null},"DispDtls":{"Nm":"RAJA ENTERPRISES","Addr1":"KHUSKIBAGH, KAPTANPARA","Addr2":null,"Loc":"PURNIA","Pin":854305,"Stcd":"10"},"ShipDtls":{"Gstin":"10CIJPB7595N1ZW","LglNm":"RAJA ENTERPRISES","TrdNm":"RAJA ENTERPRISES","Addr1":"KHUSKIBAGH, KAPTANPARA","Addr2":null,"Loc":"PURNIA","Pin":854305,"Stcd":"10"},"ValDtls":{"AssVal":360522,"IgstVal":43262.63,"CgstVal":0,"SgstVal":0,"CesVal":0,"StCesVal":0,"Discount":0,"OthChrg":0,"RndOffAmt":0.37,"TotInvVal":403785},"ExpDtls":{"ShipBNo":null,"ShipBDt":null,"Port":null,"RefClm":null,"ForCur":null,"CntCode":null,"ExpDuty":0},"EwbDtls":null,"ItemList":[{"SlNo":"1","PrdDesc":"210690","IsServc":"N","HsnCd":"210690","Barcde":null,"Qty":12000,"FreeQty":0,"Unit":"Pcs","UnitPrice":2.893,"TotAmt":34716,"Discount":0,"PreTaxVal":0,"AssAmt":34716,"GstRt":12,"IgstAmt":4165.92,"CgstAmt":0,"SgstAmt":0,"CesRt":0,"CesAmt":0,"CesNonAdvlAmt":0,"StateCesRt":0,"StateCesAmt":0,"StateCesNonAdvlAmt":0,"OthChrg":0,"TotItemVal":38881.92,"BchDtls":null},{"SlNo":"2","PrdDesc":"210690","IsServc":"N","HsnCd":"210690","Barcde":null,"Qty":2400,"FreeQty":0,"Unit":"Pcs","UnitPrice":3.17,"TotAmt":7608,"Discount":0,"PreTaxVal":0,"AssAmt":7608,"GstRt":12,"IgstAmt":912.96,"CgstAmt":0,"SgstAmt":0,"CesRt":0,"CesAmt":0,"CesNonAdvlAmt":0,"StateCesRt":0,"StateCesAmt":0,"StateCesNonAdvlAmt":0,"OthChrg":0,"TotItemVal":8520.96,"BchDtls":null},{"SlNo":"3","PrdDesc":"210690","IsServc":"N","HsnCd":"210690","Barcde":null,"Qty":4800,"FreeQty":0,"Unit":"Pcs","UnitPrice":2.893,"TotAmt":13886.4,"Discount":0,"PreTaxVal":0,"AssAmt":13886.4,"GstRt":12,"IgstAmt":1666.37,"CgstAmt":0,"SgstAmt":0,"CesRt":0,"CesAmt":0,"CesNonAdvlAmt":0,"StateCesRt":0,"StateCesAmt":0,"StateCesNonAdvlAmt":0,"OthChrg":0,"TotItemVal":15552.77,"BchDtls":null},{"SlNo":"4","PrdDesc":"210690","IsServc":"N","HsnCd":"210690","Barcde":null,"Qty":6000,"FreeQty":0,"Unit":"Pcs","UnitPrice":2.893,"TotAmt":17358,"Discount":0,"PreTaxVal":0,"AssAmt":17358,"GstRt":12,"IgstAmt":2082.96,"CgstAmt":0,"SgstAmt":0,"CesRt":0,"CesAmt":0,"CesNonAdvlAmt":0,"StateCesRt":0,"StateCesAmt":0,"StateCesNonAdvlAmt":0,"OthChrg":0,"TotItemVal":19440.96,"BchDtls":null},{"SlNo":"5","PrdDesc":"210690","IsServc":"N","HsnCd":"210690","Barcde":null,"Qty":7200,"FreeQty":0,"Unit":"Pcs","UnitPrice":2.893,"TotAmt":20829.6,"Discount":0,"PreTaxVal":0,"AssAmt":20829.6,"GstRt":12,"IgstAmt":2499.55,"CgstAmt":0,"SgstAmt":0,"CesRt":0,"CesAmt":0,"CesNonAdvlAmt":0,"StateCesRt":0,"StateCesAmt":0,"StateCesNonAdvlAmt":0,"OthChrg":0,"TotItemVal":23329.15,"BchDtls":null},{"SlNo":"6","PrdDesc":"210690","IsServc":"N","HsnCd":"210690","Barcde":null,"Qty":1200,"FreeQty":0,"Unit":"Pcs","UnitPrice":3.17,"TotAmt":3804,"Discount":0,"PreTaxVal":0,"AssAmt":3804,"GstRt":12,"IgstAmt":456.48,"CgstAmt":0,"SgstAmt":0,"CesRt":0,"CesAmt":0,"CesNonAdvlAmt":0,"StateCesRt":0,"StateCesAmt":0,"StateCesNonAdvlAmt":0,"OthChrg":0,"TotItemVal":4260.48,"BchDtls":null},{"SlNo":"7","PrdDesc":"210690","IsServc":"N","HsnCd":"210690","Barcde":null,"Qty":7200,"FreeQty":0,"Unit":"Pcs","UnitPrice":2.893,"TotAmt":20829.6,"Discount":0,"PreTaxVal":0,"AssAmt":20829.6,"GstRt":12,"IgstAmt":2499.55,"CgstAmt":0,"SgstAmt":0,"CesRt":0,"CesAmt":0,"CesNonAdvlAmt":0,"StateCesRt":0,"StateCesAmt":0,"StateCesNonAdvlAmt":0,"OthChrg":0,"TotItemVal":23329.15,"BchDtls":null},{"SlNo":"8","PrdDesc":"210690","IsServc":"N","HsnCd":"210690","Barcde":null,"Qty":2400,"FreeQty":0,"Unit":"Pcs","UnitPrice":2.893,"TotAmt":6943.2,"Discount":0,"PreTaxVal":0,"AssAmt":6943.2,"GstRt":12,"IgstAmt":833.18,"CgstAmt":0,"SgstAmt":0,"CesRt":0,"CesAmt":0,"CesNonAdvlAmt":0,"StateCesRt":0,"StateCesAmt":0,"StateCesNonAdvlAmt":0,"OthChrg":0,"TotItemVal":7776.38,"BchDtls":null},{"SlNo":"9","PrdDesc":"210690","IsServc":"N","HsnCd":"210690","Barcde":null,"Qty":76800,"FreeQty":0,"Unit":"Pcs","UnitPrice":3.054,"TotAmt":234547.2,"Discount":0,"PreTaxVal":0,"AssAmt":234547.2,"GstRt":12,"IgstAmt":28145.66,"CgstAmt":0,"SgstAmt":0,"CesRt":0,"CesAmt":0,"CesNonAdvlAmt":0,"StateCesRt":0,"StateCesAmt":0,"StateCesNonAdvlAmt":0,"OthChrg":0,"TotItemVal":262692.86,"BchDtls":null}]}]