{
    "gstin": "27AAGCG1483L1ZA",
    "ret_period": "032025",
    "sup_details": {
        "osup_det": {
            "txval": 9648473.68,
            "iamt": 0,
            "camt": 303578.35,
            "samt": 303578.35,
            "csamt": 0
        },
        "osup_zero": {
            "txval": 0,
            "iamt": 0,
            "camt": 0,
            "samt": 0,
            "csamt": 0
        },
        "osup_nil_exmp": {
            "txval": 0,
            "iamt": 0,
            "camt": 0,
            "samt": 0,
            "csamt": 0
        },
        "isup_rev": {
            "txval": 0,
            "iamt": 0,
            "camt": 0,
            "samt": 0,
            "csamt": 0
        },
        "osup_nongst": {
            "txval": 0,
            "iamt": 0,
            "camt": 0,
            "samt": 0,
            "csamt": 0
        }
    },
    "eco_dtls": {
        "eco_sup": {
            "txval": 0,
            "iamt": 0,
            "camt": 0,
            "samt": 0,
            "csamt": 0
        },
        "eco_reg_sup": {
            "txval": 0
        }
    },
    "itc_elg": {
        "itc_avl": [
            {
                "ty": "IMPG",
                "iamt": 0,
                "camt": 0,
                "samt": 0,
                "csamt": 0
            },
            {
                "ty": "ISRC",
                "iamt": 0,
                "camt": 0,
                "samt": 0,
                "csamt": 0
            },
            {
                "ty": "IMPG",
                "iamt": 0,
                "camt": 0,
                "samt": 0,
                "csamt": 0
            },
            {
                "ty": "IMPG",
                "iamt": 0,
                "camt": 0,
                "samt": 0,
                "csamt": 0
            }
        ],
        "itc_rev": [
            {
                "ty": "RUL",
                "iamt": 0,
                "camt": 0,
                "samt": 0,
                "csamt": 0
            },
            {
                "ty": "IMPG",
                "iamt": 0,
                "camt": 0,
                "samt": 0,
                "csamt": 0
            }
        ],
        "itc_net": {
            "iamt": 0,
            "camt": 0,
            "samt": 0,
            "csamt": 0
        },
        "itc_inelg": [
            {
                "ty": "RUL",
                "iamt": 0,
                "camt": 0,
                "samt": 0,
                "csamt": 0
            },
            {
                "ty": "IMPG",
                "iamt": 0,
                "camt": 0,
                "samt": 0,
                "csamt": 0
            }
        ]
    },
    "inward_sup": {
        "isup_details": [
            {
                "ty": 0,
                "inter": 0,
                "intra": 0
            },
            {
                "ty": 0,
                "inter": 0,
                "intra": 0
            }
        ]
    },
    "intr_ltfee": {
        "intr_details": {
            "iamt": 0,
            "camt": 0,
            "samt": 0,
            "csamt": 0
        },
        "ltfee_details": []
    },
    "inter_sup": {
        "unreg_details": [],
        "comp_details": [],
        "uin_details": []
    }
}