[{"Version":"1.1","TranDtls":{"TaxSch":"GST","SupTyp":"B2B","IgstOnIntra":"N","RegRev":"N","EcmGstin":null},"DocDtls":{"Typ":"INV","No":"TAX23104444","Dt":"02\/09\/2023"},"SellerDtls":{"Gstin":"09AADCC2371G1ZT","LglNm":"Crazy Snacks Pvt. Ltd.","TrdNm":"Crazy Snacks Pvt. Ltd.","Addr1":"DL-2, Sector-13,GIDA, Sahjanwa Road, Gorakhpur, Uttar Pradesh","Addr2":null,"Loc":"Gorakhpur","Pin":273209,"Stcd":"09","Ph":"9838070286"},"BuyerDtls":{"Gstin":"09DUHPK4138K1Z8","LglNm":"VINOD ENTERPRISES","TrdNm":"VINOD ENTERPRISES","Pos":"9","Addr1":"CHILHIYA, SHOHRATGARH","Addr2":null,"Loc":"SIDDHARTH NAGAR","Pin":272204,"Stcd":"9","Ph":null},"DispDtls":{"Nm":"VINOD ENTERPRISES","Addr1":"CHILHIYA, SHOHRATGARH","Addr2":null,"Loc":"SIDDHARTH NAGAR","Pin":272204,"Stcd":"9"},"ShipDtls":{"Gstin":"09DUHPK4138K1Z8","LglNm":"VINOD ENTERPRISES","TrdNm":"VINOD ENTERPRISES","Addr1":"CHILHIYA, SHOHRATGARH","Addr2":null,"Loc":"SIDDHARTH NAGAR","Pin":272204,"Stcd":"9"},"ValDtls":{"AssVal":121924,"IgstVal":0,"CgstVal":3048.36,"SgstVal":3048.36,"CesVal":0,"StCesVal":0,"Discount":0,"OthChrg":0,"RndOffAmt":0.28,"TotInvVal":128021},"ExpDtls":{"ShipBNo":null,"ShipBDt":null,"Port":null,"RefClm":null,"ForCur":null,"CntCode":null,"ExpDuty":0},"EwbDtls":null,"ItemList":[{"SlNo":"1","PrdDesc":"19054000","IsServc":"N","HsnCd":"19054000","Barcde":null,"Qty":5000,"FreeQty":0,"Unit":"Pcs","UnitPrice":7.62,"TotAmt":38100,"Discount":0,"PreTaxVal":0,"AssAmt":38100,"GstRt":5,"IgstAmt":0,"CgstAmt":952.5,"SgstAmt":952.5,"CesRt":0,"CesAmt":0,"CesNonAdvlAmt":0,"StateCesRt":0,"StateCesAmt":0,"StateCesNonAdvlAmt":0,"OthChrg":0,"TotItemVal":40005,"BchDtls":null},{"SlNo":"2","PrdDesc":"19054000","IsServc":"N","HsnCd":"19054000","Barcde":null,"Qty":4400,"FreeQty":0,"Unit":"Pcs","UnitPrice":19.05,"TotAmt":83820,"Discount":0,"PreTaxVal":0,"AssAmt":83820,"GstRt":5,"IgstAmt":0,"CgstAmt":2095.5,"SgstAmt":2095.5,"CesRt":0,"CesAmt":0,"CesNonAdvlAmt":0,"StateCesRt":0,"StateCesAmt":0,"StateCesNonAdvlAmt":0,"OthChrg":0,"TotItemVal":88011,"BchDtls":null},{"SlNo":"3","PrdDesc":"48211090","IsServc":"N","HsnCd":"48211090","Barcde":null,"Qty":400,"FreeQty":0,"Unit":"Pcs","UnitPrice":0.01,"TotAmt":4,"Discount":0,"PreTaxVal":0,"AssAmt":4,"GstRt":18,"IgstAmt":0,"CgstAmt":0.36,"SgstAmt":0.36,"CesRt":0,"CesAmt":0,"CesNonAdvlAmt":0,"StateCesRt":0,"StateCesAmt":0,"StateCesNonAdvlAmt":0,"OthChrg":0,"TotItemVal":4.72,"BchDtls":null}]}]