[{"Version":"1.1","TranDtls":{"TaxSch":"GST","SupTyp":"B2B","IgstOnIntra":"N","RegRev":"N","EcmGstin":null},"DocDtls":{"Typ":"INV","No":"TAX22103576","Dt":"08\/08\/2022"},"SellerDtls":{"Gstin":"09AADCC2371G1ZT","LglNm":"Crazy Snacks Pvt. Ltd.","TrdNm":"Crazy Snacks Pvt. Ltd.","Addr1":"DL-2, Sector-13,GIDA, Sahjanwa Road, Gorakhpur, Uttar Pradesh","Addr2":null,"Loc":"Gorakhpur","Pin":273209,"Stcd":"09","Ph":"9838070286"},"BuyerDtls":{"Gstin":"09AAMFC6710F2ZG","LglNm":"CRAZY BAKERY UDYOG","TrdNm":"CRAZY BAKERY UDYOG","Pos":"9","Addr1":"SEC-15","Addr2":null,"Loc":"GORAKHPUR","Pin":273209,"Stcd":"9","Ph":null},"DispDtls":{"Nm":"CRAZY BAKERY UDYOG","Addr1":"SEC-15","Addr2":null,"Loc":"GORAKHPUR","Pin":273209,"Stcd":"9"},"ShipDtls":{"Gstin":"09AAMFC6710F2ZG","LglNm":"CRAZY BAKERY UDYOG","TrdNm":"CRAZY BAKERY UDYOG","Addr1":"SEC-15","Addr2":null,"Loc":"GORAKHPUR","Pin":273209,"Stcd":"9"},"ValDtls":{"AssVal":205070.4,"IgstVal":0,"CgstVal":18456.34,"SgstVal":18456.34,"CesVal":0,"StCesVal":0,"Discount":0,"OthChrg":0,"RndOffAmt":-0.07,"TotInvVal":241983},"ExpDtls":{"ShipBNo":null,"ShipBDt":null,"Port":null,"RefClm":null,"ForCur":null,"CntCode":null,"ExpDuty":0},"EwbDtls":null,"ItemList":[{"SlNo":"1","PrdDesc":"190590","IsServc":"N","HsnCd":"190590","Barcde":null,"Qty":31320,"FreeQty":0,"Unit":"Pcs","UnitPrice":2.82,"TotAmt":88322.4,"Discount":0,"PreTaxVal":0,"AssAmt":88322.4,"GstRt":18,"IgstAmt":0,"CgstAmt":7949.02,"SgstAmt":7949.02,"CesRt":0,"CesAmt":0,"CesNonAdvlAmt":0,"StateCesRt":0,"StateCesAmt":0,"StateCesNonAdvlAmt":0,"OthChrg":0,"TotItemVal":104220.43,"BchDtls":null},{"SlNo":"2","PrdDesc":"19059010","IsServc":"N","HsnCd":"19059010","Barcde":null,"Qty":27000,"FreeQty":0,"Unit":"Pcs","UnitPrice":2.82,"TotAmt":76140,"Discount":0,"PreTaxVal":0,"AssAmt":76140,"GstRt":18,"IgstAmt":0,"CgstAmt":6852.6,"SgstAmt":6852.6,"CesRt":0,"CesAmt":0,"CesNonAdvlAmt":0,"StateCesRt":0,"StateCesAmt":0,"StateCesNonAdvlAmt":0,"OthChrg":0,"TotItemVal":89845.2,"BchDtls":null},{"SlNo":"3","PrdDesc":"19059010","IsServc":"N","HsnCd":"19059010","Barcde":null,"Qty":14400,"FreeQty":0,"Unit":"Pcs","UnitPrice":2.82,"TotAmt":40608,"Discount":0,"PreTaxVal":0,"AssAmt":40608,"GstRt":18,"IgstAmt":0,"CgstAmt":3654.72,"SgstAmt":3654.72,"CesRt":0,"CesAmt":0,"CesNonAdvlAmt":0,"StateCesRt":0,"StateCesAmt":0,"StateCesNonAdvlAmt":0,"OthChrg":0,"TotItemVal":47917.44,"BchDtls":null}]}]