[{"Version":"1.1","TranDtls":{"TaxSch":"GST","SupTyp":"B2B","IgstOnIntra":"N","RegRev":"N","EcmGstin":null},"DocDtls":{"Typ":"INV","No":"TAX23102221","Dt":"25\/06\/2023"},"SellerDtls":{"Gstin":"09AADCC2371G1ZT","LglNm":"Crazy Snacks Pvt. Ltd.","TrdNm":"Crazy Snacks Pvt. Ltd.","Addr1":"DL-2, Sector-13,GIDA, Sahjanwa Road, Gorakhpur, Uttar Pradesh","Addr2":null,"Loc":"Gorakhpur","Pin":273209,"Stcd":"09","Ph":"9838070286"},"BuyerDtls":{"Gstin":"09BPCPK1495K1ZJ","LglNm":"V.P BREAD AGENCY","TrdNm":"V.P BREAD AGENCY","Pos":"9","Addr1":"KAURIRAM","Addr2":null,"Loc":"GORAKHPUR","Pin":273413,"Stcd":"9","Ph":null},"DispDtls":{"Nm":"V.P BREAD AGENCY","Addr1":"KAURIRAM","Addr2":null,"Loc":"GORAKHPUR","Pin":273413,"Stcd":"9"},"ShipDtls":{"Gstin":"09BPCPK1495K1ZJ","LglNm":"V.P BREAD AGENCY","TrdNm":"V.P BREAD AGENCY","Addr1":"KAURIRAM","Addr2":null,"Loc":"GORAKHPUR","Pin":273413,"Stcd":"9"},"ValDtls":{"AssVal":129254,"IgstVal":0,"CgstVal":3231.35,"SgstVal":3231.35,"CesVal":0,"StCesVal":0,"Discount":0,"OthChrg":0,"RndOffAmt":0.3,"TotInvVal":135717},"ExpDtls":{"ShipBNo":null,"ShipBDt":null,"Port":null,"RefClm":null,"ForCur":null,"CntCode":null,"ExpDuty":0},"EwbDtls":null,"ItemList":[{"SlNo":"1","PrdDesc":"19054000","IsServc":"N","HsnCd":"19054000","Barcde":null,"Qty":4800,"FreeQty":0,"Unit":"Pcs","UnitPrice":8.13,"TotAmt":39024,"Discount":0,"PreTaxVal":0,"AssAmt":39024,"GstRt":5,"IgstAmt":0,"CgstAmt":975.6,"SgstAmt":975.6,"CesRt":0,"CesAmt":0,"CesNonAdvlAmt":0,"StateCesRt":0,"StateCesAmt":0,"StateCesNonAdvlAmt":0,"OthChrg":0,"TotItemVal":40975.2,"BchDtls":null},{"SlNo":"2","PrdDesc":"19054000","IsServc":"N","HsnCd":"19054000","Barcde":null,"Qty":2000,"FreeQty":0,"Unit":"Pcs","UnitPrice":14.52,"TotAmt":29040,"Discount":0,"PreTaxVal":0,"AssAmt":29040,"GstRt":5,"IgstAmt":0,"CgstAmt":726,"SgstAmt":726,"CesRt":0,"CesAmt":0,"CesNonAdvlAmt":0,"StateCesRt":0,"StateCesAmt":0,"StateCesNonAdvlAmt":0,"OthChrg":0,"TotItemVal":30492,"BchDtls":null},{"SlNo":"3","PrdDesc":"19054000","IsServc":"N","HsnCd":"19054000","Barcde":null,"Qty":800,"FreeQty":0,"Unit":"Pcs","UnitPrice":17.56,"TotAmt":14048,"Discount":0,"PreTaxVal":0,"AssAmt":14048,"GstRt":5,"IgstAmt":0,"CgstAmt":351.2,"SgstAmt":351.2,"CesRt":0,"CesAmt":0,"CesNonAdvlAmt":0,"StateCesRt":0,"StateCesAmt":0,"StateCesNonAdvlAmt":0,"OthChrg":0,"TotItemVal":14750.4,"BchDtls":null},{"SlNo":"4","PrdDesc":"19054000","IsServc":"N","HsnCd":"19054000","Barcde":null,"Qty":6000,"FreeQty":0,"Unit":"Pcs","UnitPrice":7.857,"TotAmt":47142,"Discount":0,"PreTaxVal":0,"AssAmt":47142,"GstRt":5,"IgstAmt":0,"CgstAmt":1178.55,"SgstAmt":1178.55,"CesRt":0,"CesAmt":0,"CesNonAdvlAmt":0,"StateCesRt":0,"StateCesAmt":0,"StateCesNonAdvlAmt":0,"OthChrg":0,"TotItemVal":49499.1,"BchDtls":null}]}]