[{"Version":"1.1","TranDtls":{"TaxSch":"GST","SupTyp":"B2B","IgstOnIntra":"N","RegRev":"N","EcmGstin":null},"DocDtls":{"Typ":"INV","No":"TAX22301075","Dt":"22\/06\/2022"},"SellerDtls":{"Gstin":"09AAMFC6710F2ZG","LglNm":"CRAZY BAKERY UDYOG","TrdNm":"CRAZY BAKERY UDYOG","Addr1":"PLOT NO. G-3A, SECTOR-15, GIDA, Sahjanwa Road, Gorakhpur","Addr2":null,"Loc":"Gorakhpur","Pin":273209,"Stcd":"09","Ph":"9838755227"},"BuyerDtls":{"Gstin":"19ADDPC4687P1ZX","LglNm":"CHOWDHARY PAN GHAR","TrdNm":"CHOWDHARY PAN GHAR","Pos":"19","Addr1":"BARA BAZAR, P.O. - BIRPARA","Addr2":null,"Loc":"JALPAIGURI","Pin":735204,"Stcd":"19","Ph":null},"DispDtls":{"Nm":"CHOWDHARY PAN GHAR","Addr1":"BARA BAZAR, P.O. - BIRPARA","Addr2":null,"Loc":"JALPAIGURI","Pin":735204,"Stcd":"19"},"ShipDtls":{"Gstin":"19ADDPC4687P1ZX","LglNm":"CHOWDHARY PAN GHAR","TrdNm":"CHOWDHARY PAN GHAR","Addr1":"BARA BAZAR, P.O. - BIRPARA","Addr2":null,"Loc":"JALPAIGURI","Pin":735204,"Stcd":"19"},"ValDtls":{"AssVal":189808.8,"IgstVal":11998.29,"CgstVal":0,"SgstVal":0,"CesVal":0,"StCesVal":0,"Discount":0,"OthChrg":0,"RndOffAmt":-0.09,"TotInvVal":201807},"ExpDtls":{"ShipBNo":null,"ShipBDt":null,"Port":null,"RefClm":null,"ForCur":null,"CntCode":null,"ExpDuty":0},"EwbDtls":null,"ItemList":[{"SlNo":"1","PrdDesc":"210690","IsServc":"N","HsnCd":"210690","Barcde":null,"Qty":5760,"FreeQty":0,"Unit":"Pcs","UnitPrice":3.43,"TotAmt":19756.8,"Discount":0,"PreTaxVal":0,"AssAmt":19756.8,"GstRt":5,"IgstAmt":987.84,"CgstAmt":0,"SgstAmt":0,"CesRt":0,"CesAmt":0,"CesNonAdvlAmt":0,"StateCesRt":0,"StateCesAmt":0,"StateCesNonAdvlAmt":0,"OthChrg":0,"TotItemVal":20744.64,"BchDtls":null},{"SlNo":"2","PrdDesc":"210690","IsServc":"N","HsnCd":"210690","Barcde":null,"Qty":2160,"FreeQty":0,"Unit":"Pcs","UnitPrice":3.43,"TotAmt":7408.8,"Discount":0,"PreTaxVal":0,"AssAmt":7408.8,"GstRt":5,"IgstAmt":370.44,"CgstAmt":0,"SgstAmt":0,"CesRt":0,"CesAmt":0,"CesNonAdvlAmt":0,"StateCesRt":0,"StateCesAmt":0,"StateCesNonAdvlAmt":0,"OthChrg":0,"TotItemVal":7779.24,"BchDtls":null},{"SlNo":"3","PrdDesc":"210690","IsServc":"N","HsnCd":"210690","Barcde":null,"Qty":2400,"FreeQty":0,"Unit":"Pcs","UnitPrice":3.09,"TotAmt":7416,"Discount":0,"PreTaxVal":0,"AssAmt":7416,"GstRt":5,"IgstAmt":370.8,"CgstAmt":0,"SgstAmt":0,"CesRt":0,"CesAmt":0,"CesNonAdvlAmt":0,"StateCesRt":0,"StateCesAmt":0,"StateCesNonAdvlAmt":0,"OthChrg":0,"TotItemVal":7786.8,"BchDtls":null},{"SlNo":"4","PrdDesc":"210690","IsServc":"N","HsnCd":"210690","Barcde":null,"Qty":12000,"FreeQty":0,"Unit":"Pcs","UnitPrice":3.09,"TotAmt":37080,"Discount":0,"PreTaxVal":0,"AssAmt":37080,"GstRt":5,"IgstAmt":1854,"CgstAmt":0,"SgstAmt":0,"CesRt":0,"CesAmt":0,"CesNonAdvlAmt":0,"StateCesRt":0,"StateCesAmt":0,"StateCesNonAdvlAmt":0,"OthChrg":0,"TotItemVal":38934,"BchDtls":null},{"SlNo":"5","PrdDesc":"210690","IsServc":"N","HsnCd":"210690","Barcde":null,"Qty":14400,"FreeQty":0,"Unit":"Pcs","UnitPrice":3.09,"TotAmt":44496,"Discount":0,"PreTaxVal":0,"AssAmt":44496,"GstRt":5,"IgstAmt":2224.8,"CgstAmt":0,"SgstAmt":0,"CesRt":0,"CesAmt":0,"CesNonAdvlAmt":0,"StateCesRt":0,"StateCesAmt":0,"StateCesNonAdvlAmt":0,"OthChrg":0,"TotItemVal":46720.8,"BchDtls":null},{"SlNo":"6","PrdDesc":"210690","IsServc":"N","HsnCd":"210690","Barcde":null,"Qty":2400,"FreeQty":0,"Unit":"Pcs","UnitPrice":3.09,"TotAmt":7416,"Discount":0,"PreTaxVal":0,"AssAmt":7416,"GstRt":5,"IgstAmt":370.8,"CgstAmt":0,"SgstAmt":0,"CesRt":0,"CesAmt":0,"CesNonAdvlAmt":0,"StateCesRt":0,"StateCesAmt":0,"StateCesNonAdvlAmt":0,"OthChrg":0,"TotItemVal":7786.8,"BchDtls":null},{"SlNo":"7","PrdDesc":"190590","IsServc":"N","HsnCd":"190590","Barcde":null,"Qty":720,"FreeQty":0,"Unit":"Pcs","UnitPrice":2.82,"TotAmt":2030.4,"Discount":0,"PreTaxVal":0,"AssAmt":2030.4,"GstRt":18,"IgstAmt":365.47,"CgstAmt":0,"SgstAmt":0,"CesRt":0,"CesAmt":0,"CesNonAdvlAmt":0,"StateCesRt":0,"StateCesAmt":0,"StateCesNonAdvlAmt":0,"OthChrg":0,"TotItemVal":2395.87,"BchDtls":null},{"SlNo":"8","PrdDesc":"190590","IsServc":"N","HsnCd":"190590","Barcde":null,"Qty":720,"FreeQty":0,"Unit":"Pcs","UnitPrice":2.82,"TotAmt":2030.4,"Discount":0,"PreTaxVal":0,"AssAmt":2030.4,"GstRt":18,"IgstAmt":365.47,"CgstAmt":0,"SgstAmt":0,"CesRt":0,"CesAmt":0,"CesNonAdvlAmt":0,"StateCesRt":0,"StateCesAmt":0,"StateCesNonAdvlAmt":0,"OthChrg":0,"TotItemVal":2395.87,"BchDtls":null},{"SlNo":"9","PrdDesc":"1806","IsServc":"N","HsnCd":"1806","Barcde":null,"Qty":1200,"FreeQty":0,"Unit":"Pcs","UnitPrice":2.54,"TotAmt":3048,"Discount":0,"PreTaxVal":0,"AssAmt":3048,"GstRt":18,"IgstAmt":548.64,"CgstAmt":0,"SgstAmt":0,"CesRt":0,"CesAmt":0,"CesNonAdvlAmt":0,"StateCesRt":0,"StateCesAmt":0,"StateCesNonAdvlAmt":0,"OthChrg":0,"TotItemVal":3596.64,"BchDtls":null},{"SlNo":"10","PrdDesc":"190590","IsServc":"N","HsnCd":"190590","Barcde":null,"Qty":1440,"FreeQty":0,"Unit":"Pcs","UnitPrice":2.82,"TotAmt":4060.8,"Discount":0,"PreTaxVal":0,"AssAmt":4060.8,"GstRt":18,"IgstAmt":730.94,"CgstAmt":0,"SgstAmt":0,"CesRt":0,"CesAmt":0,"CesNonAdvlAmt":0,"StateCesRt":0,"StateCesAmt":0,"StateCesNonAdvlAmt":0,"OthChrg":0,"TotItemVal":4791.74,"BchDtls":null},{"SlNo":"11","PrdDesc":"190590","IsServc":"N","HsnCd":"190590","Barcde":null,"Qty":1080,"FreeQty":0,"Unit":"Pcs","UnitPrice":2.82,"TotAmt":3045.6,"Discount":0,"PreTaxVal":0,"AssAmt":3045.6,"GstRt":18,"IgstAmt":548.21,"CgstAmt":0,"SgstAmt":0,"CesRt":0,"CesAmt":0,"CesNonAdvlAmt":0,"StateCesRt":0,"StateCesAmt":0,"StateCesNonAdvlAmt":0,"OthChrg":0,"TotItemVal":3593.81,"BchDtls":null},{"SlNo":"12","PrdDesc":"190590","IsServc":"N","HsnCd":"190590","Barcde":null,"Qty":1800,"FreeQty":0,"Unit":"Pcs","UnitPrice":2.82,"TotAmt":5076,"Discount":0,"PreTaxVal":0,"AssAmt":5076,"GstRt":18,"IgstAmt":913.68,"CgstAmt":0,"SgstAmt":0,"CesRt":0,"CesAmt":0,"CesNonAdvlAmt":0,"StateCesRt":0,"StateCesAmt":0,"StateCesNonAdvlAmt":0,"OthChrg":0,"TotItemVal":5989.68,"BchDtls":null},{"SlNo":"13","PrdDesc":"210690","IsServc":"N","HsnCd":"210690","Barcde":null,"Qty":14400,"FreeQty":0,"Unit":"Pcs","UnitPrice":3.26,"TotAmt":46944,"Discount":0,"PreTaxVal":0,"AssAmt":46944,"GstRt":5,"IgstAmt":2347.2,"CgstAmt":0,"SgstAmt":0,"CesRt":0,"CesAmt":0,"CesNonAdvlAmt":0,"StateCesRt":0,"StateCesAmt":0,"StateCesNonAdvlAmt":0,"OthChrg":0,"TotItemVal":49291.2,"BchDtls":null}]}]