[{"Version":"1.1","TranDtls":{"TaxSch":"GST","SupTyp":"B2B","IgstOnIntra":"N","RegRev":"N","EcmGstin":null},"DocDtls":{"Typ":"INV","No":"TAX22300175","Dt":"19\/04\/2022"},"SellerDtls":{"Gstin":"09AAMFC6710F2ZG","LglNm":"CRAZY BAKERY UDYOG","TrdNm":"CRAZY BAKERY UDYOG","Addr1":"PLOT NO. G-3A, SECTOR-15, GIDA, Sahjanwa Road, Gorakhpur","Addr2":null,"Loc":"Gorakhpur","Pin":273209,"Stcd":"09","Ph":"9838755227"},"BuyerDtls":{"Gstin":"09BTKPD9998L1ZK","LglNm":"JAISWAL KIRANA STORE","TrdNm":"JAISWAL KIRANA STORE","Pos":"9","Addr1":"KARDA ,WAZEERGANJ,TARABGANJ","Addr2":null,"Loc":"GONDA","Pin":271124,"Stcd":"9","Ph":null},"DispDtls":{"Nm":"JAISWAL KIRANA STORE","Addr1":"KARDA ,WAZEERGANJ,TARABGANJ","Addr2":null,"Loc":"GONDA","Pin":271124,"Stcd":"9"},"ShipDtls":{"Gstin":"09BTKPD9998L1ZK","LglNm":"JAISWAL KIRANA STORE","TrdNm":"JAISWAL KIRANA STORE","Addr1":"KARDA ,WAZEERGANJ,TARABGANJ","Addr2":null,"Loc":"GONDA","Pin":271124,"Stcd":"9"},"ValDtls":{"AssVal":72035.04,"IgstVal":0,"CgstVal":1800.87,"SgstVal":1800.87,"CesVal":0,"StCesVal":0,"Discount":0,"OthChrg":0,"RndOffAmt":0.21,"TotInvVal":75637},"ExpDtls":{"ShipBNo":null,"ShipBDt":null,"Port":null,"RefClm":null,"ForCur":null,"CntCode":null,"ExpDuty":0},"EwbDtls":null,"ItemList":[{"SlNo":"1","PrdDesc":"210690","IsServc":"N","HsnCd":"210690","Barcde":null,"Qty":1200,"FreeQty":0,"Unit":"Pcs","UnitPrice":3.49,"TotAmt":4188,"Discount":0,"PreTaxVal":0,"AssAmt":4188,"GstRt":5,"IgstAmt":0,"CgstAmt":104.7,"SgstAmt":104.7,"CesRt":0,"CesAmt":0,"CesNonAdvlAmt":0,"StateCesRt":0,"StateCesAmt":0,"StateCesNonAdvlAmt":0,"OthChrg":0,"TotItemVal":4397.4,"BchDtls":null},{"SlNo":"2","PrdDesc":"210690","IsServc":"N","HsnCd":"210690","Barcde":null,"Qty":1200,"FreeQty":0,"Unit":"Pcs","UnitPrice":3.49,"TotAmt":4188,"Discount":0,"PreTaxVal":0,"AssAmt":4188,"GstRt":5,"IgstAmt":0,"CgstAmt":104.7,"SgstAmt":104.7,"CesRt":0,"CesAmt":0,"CesNonAdvlAmt":0,"StateCesRt":0,"StateCesAmt":0,"StateCesNonAdvlAmt":0,"OthChrg":0,"TotItemVal":4397.4,"BchDtls":null},{"SlNo":"3","PrdDesc":"210690","IsServc":"N","HsnCd":"210690","Barcde":null,"Qty":1200,"FreeQty":0,"Unit":"Pcs","UnitPrice":3.49,"TotAmt":4188,"Discount":0,"PreTaxVal":0,"AssAmt":4188,"GstRt":5,"IgstAmt":0,"CgstAmt":104.7,"SgstAmt":104.7,"CesRt":0,"CesAmt":0,"CesNonAdvlAmt":0,"StateCesRt":0,"StateCesAmt":0,"StateCesNonAdvlAmt":0,"OthChrg":0,"TotItemVal":4397.4,"BchDtls":null},{"SlNo":"4","PrdDesc":"210690","IsServc":"N","HsnCd":"210690","Barcde":null,"Qty":1200,"FreeQty":0,"Unit":"Pcs","UnitPrice":3.49,"TotAmt":4188,"Discount":0,"PreTaxVal":0,"AssAmt":4188,"GstRt":5,"IgstAmt":0,"CgstAmt":104.7,"SgstAmt":104.7,"CesRt":0,"CesAmt":0,"CesNonAdvlAmt":0,"StateCesRt":0,"StateCesAmt":0,"StateCesNonAdvlAmt":0,"OthChrg":0,"TotItemVal":4397.4,"BchDtls":null},{"SlNo":"5","PrdDesc":"210690","IsServc":"N","HsnCd":"210690","Barcde":null,"Qty":1200,"FreeQty":0,"Unit":"Pcs","UnitPrice":3.49,"TotAmt":4188,"Discount":0,"PreTaxVal":0,"AssAmt":4188,"GstRt":5,"IgstAmt":0,"CgstAmt":104.7,"SgstAmt":104.7,"CesRt":0,"CesAmt":0,"CesNonAdvlAmt":0,"StateCesRt":0,"StateCesAmt":0,"StateCesNonAdvlAmt":0,"OthChrg":0,"TotItemVal":4397.4,"BchDtls":null},{"SlNo":"6","PrdDesc":"210690","IsServc":"N","HsnCd":"210690","Barcde":null,"Qty":1200,"FreeQty":0,"Unit":"Pcs","UnitPrice":3.49,"TotAmt":4188,"Discount":0,"PreTaxVal":0,"AssAmt":4188,"GstRt":5,"IgstAmt":0,"CgstAmt":104.7,"SgstAmt":104.7,"CesRt":0,"CesAmt":0,"CesNonAdvlAmt":0,"StateCesRt":0,"StateCesAmt":0,"StateCesNonAdvlAmt":0,"OthChrg":0,"TotItemVal":4397.4,"BchDtls":null},{"SlNo":"7","PrdDesc":"210690","IsServc":"N","HsnCd":"210690","Barcde":null,"Qty":720,"FreeQty":0,"Unit":"Pcs","UnitPrice":3.49,"TotAmt":2512.8,"Discount":0,"PreTaxVal":0,"AssAmt":2512.8,"GstRt":5,"IgstAmt":0,"CgstAmt":62.82,"SgstAmt":62.82,"CesRt":0,"CesAmt":0,"CesNonAdvlAmt":0,"StateCesRt":0,"StateCesAmt":0,"StateCesNonAdvlAmt":0,"OthChrg":0,"TotItemVal":2638.44,"BchDtls":null},{"SlNo":"8","PrdDesc":"210690","IsServc":"N","HsnCd":"210690","Barcde":null,"Qty":720,"FreeQty":0,"Unit":"Pcs","UnitPrice":3.49,"TotAmt":2512.8,"Discount":0,"PreTaxVal":0,"AssAmt":2512.8,"GstRt":5,"IgstAmt":0,"CgstAmt":62.82,"SgstAmt":62.82,"CesRt":0,"CesAmt":0,"CesNonAdvlAmt":0,"StateCesRt":0,"StateCesAmt":0,"StateCesNonAdvlAmt":0,"OthChrg":0,"TotItemVal":2638.44,"BchDtls":null},{"SlNo":"9","PrdDesc":"210690","IsServc":"N","HsnCd":"210690","Barcde":null,"Qty":1440,"FreeQty":0,"Unit":"Pcs","UnitPrice":3.49,"TotAmt":5025.6,"Discount":0,"PreTaxVal":0,"AssAmt":5025.6,"GstRt":5,"IgstAmt":0,"CgstAmt":125.64,"SgstAmt":125.64,"CesRt":0,"CesAmt":0,"CesNonAdvlAmt":0,"StateCesRt":0,"StateCesAmt":0,"StateCesNonAdvlAmt":0,"OthChrg":0,"TotItemVal":5276.88,"BchDtls":null},{"SlNo":"10","PrdDesc":"210690","IsServc":"N","HsnCd":"210690","Barcde":null,"Qty":720,"FreeQty":0,"Unit":"Pcs","UnitPrice":3.49,"TotAmt":2512.8,"Discount":0,"PreTaxVal":0,"AssAmt":2512.8,"GstRt":5,"IgstAmt":0,"CgstAmt":62.82,"SgstAmt":62.82,"CesRt":0,"CesAmt":0,"CesNonAdvlAmt":0,"StateCesRt":0,"StateCesAmt":0,"StateCesNonAdvlAmt":0,"OthChrg":0,"TotItemVal":2638.44,"BchDtls":null},{"SlNo":"11","PrdDesc":"210690","IsServc":"N","HsnCd":"210690","Barcde":null,"Qty":720,"FreeQty":0,"Unit":"Pcs","UnitPrice":3.49,"TotAmt":2512.8,"Discount":0,"PreTaxVal":0,"AssAmt":2512.8,"GstRt":5,"IgstAmt":0,"CgstAmt":62.82,"SgstAmt":62.82,"CesRt":0,"CesAmt":0,"CesNonAdvlAmt":0,"StateCesRt":0,"StateCesAmt":0,"StateCesNonAdvlAmt":0,"OthChrg":0,"TotItemVal":2638.44,"BchDtls":null},{"SlNo":"12","PrdDesc":"210690","IsServc":"N","HsnCd":"210690","Barcde":null,"Qty":2592,"FreeQty":0,"Unit":"Pcs","UnitPrice":3.49,"TotAmt":9046.08,"Discount":0,"PreTaxVal":0,"AssAmt":9046.08,"GstRt":5,"IgstAmt":0,"CgstAmt":226.15,"SgstAmt":226.15,"CesRt":0,"CesAmt":0,"CesNonAdvlAmt":0,"StateCesRt":0,"StateCesAmt":0,"StateCesNonAdvlAmt":0,"OthChrg":0,"TotItemVal":9498.38,"BchDtls":null},{"SlNo":"13","PrdDesc":"210690","IsServc":"N","HsnCd":"210690","Barcde":null,"Qty":720,"FreeQty":0,"Unit":"Pcs","UnitPrice":3.49,"TotAmt":2512.8,"Discount":0,"PreTaxVal":0,"AssAmt":2512.8,"GstRt":5,"IgstAmt":0,"CgstAmt":62.82,"SgstAmt":62.82,"CesRt":0,"CesAmt":0,"CesNonAdvlAmt":0,"StateCesRt":0,"StateCesAmt":0,"StateCesNonAdvlAmt":0,"OthChrg":0,"TotItemVal":2638.44,"BchDtls":null},{"SlNo":"14","PrdDesc":"210690","IsServc":"N","HsnCd":"210690","Barcde":null,"Qty":960,"FreeQty":0,"Unit":"Pcs","UnitPrice":3.49,"TotAmt":3350.4,"Discount":0,"PreTaxVal":0,"AssAmt":3350.4,"GstRt":5,"IgstAmt":0,"CgstAmt":83.76,"SgstAmt":83.76,"CesRt":0,"CesAmt":0,"CesNonAdvlAmt":0,"StateCesRt":0,"StateCesAmt":0,"StateCesNonAdvlAmt":0,"OthChrg":0,"TotItemVal":3517.92,"BchDtls":null},{"SlNo":"15","PrdDesc":"210690","IsServc":"N","HsnCd":"210690","Barcde":null,"Qty":960,"FreeQty":0,"Unit":"Pcs","UnitPrice":3.49,"TotAmt":3350.4,"Discount":0,"PreTaxVal":0,"AssAmt":3350.4,"GstRt":5,"IgstAmt":0,"CgstAmt":83.76,"SgstAmt":83.76,"CesRt":0,"CesAmt":0,"CesNonAdvlAmt":0,"StateCesRt":0,"StateCesAmt":0,"StateCesNonAdvlAmt":0,"OthChrg":0,"TotItemVal":3517.92,"BchDtls":null},{"SlNo":"16","PrdDesc":"210690","IsServc":"N","HsnCd":"210690","Barcde":null,"Qty":1920,"FreeQty":0,"Unit":"Pcs","UnitPrice":3.49,"TotAmt":6700.8,"Discount":0,"PreTaxVal":0,"AssAmt":6700.8,"GstRt":5,"IgstAmt":0,"CgstAmt":167.52,"SgstAmt":167.52,"CesRt":0,"CesAmt":0,"CesNonAdvlAmt":0,"StateCesRt":0,"StateCesAmt":0,"StateCesNonAdvlAmt":0,"OthChrg":0,"TotItemVal":7035.84,"BchDtls":null},{"SlNo":"17","PrdDesc":"210690","IsServc":"N","HsnCd":"210690","Barcde":null,"Qty":960,"FreeQty":0,"Unit":"Pcs","UnitPrice":3.49,"TotAmt":3350.4,"Discount":0,"PreTaxVal":0,"AssAmt":3350.4,"GstRt":5,"IgstAmt":0,"CgstAmt":83.76,"SgstAmt":83.76,"CesRt":0,"CesAmt":0,"CesNonAdvlAmt":0,"StateCesRt":0,"StateCesAmt":0,"StateCesNonAdvlAmt":0,"OthChrg":0,"TotItemVal":3517.92,"BchDtls":null},{"SlNo":"18","PrdDesc":"210690","IsServc":"N","HsnCd":"210690","Barcde":null,"Qty":720,"FreeQty":0,"Unit":"Pcs","UnitPrice":3.49,"TotAmt":2512.8,"Discount":0,"PreTaxVal":0,"AssAmt":2512.8,"GstRt":5,"IgstAmt":0,"CgstAmt":62.82,"SgstAmt":62.82,"CesRt":0,"CesAmt":0,"CesNonAdvlAmt":0,"StateCesRt":0,"StateCesAmt":0,"StateCesNonAdvlAmt":0,"OthChrg":0,"TotItemVal":2638.44,"BchDtls":null},{"SlNo":"19","PrdDesc":"210690","IsServc":"N","HsnCd":"210690","Barcde":null,"Qty":72,"FreeQty":0,"Unit":"Pcs","UnitPrice":13.98,"TotAmt":1006.56,"Discount":0,"PreTaxVal":0,"AssAmt":1006.56,"GstRt":5,"IgstAmt":0,"CgstAmt":25.16,"SgstAmt":25.16,"CesRt":0,"CesAmt":0,"CesNonAdvlAmt":0,"StateCesRt":0,"StateCesAmt":0,"StateCesNonAdvlAmt":0,"OthChrg":0,"TotItemVal":1056.89,"BchDtls":null}]}]