[{"Version":"1.1","TranDtls":{"TaxSch":"GST","SupTyp":"B2B","IgstOnIntra":"N","RegRev":"N","EcmGstin":null},"DocDtls":{"Typ":"INV","No":"TAX22300222","Dt":"23\/04\/2022"},"SellerDtls":{"Gstin":"09AAMFC6710F2ZG","LglNm":"CRAZY BAKERY UDYOG","TrdNm":"CRAZY BAKERY UDYOG","Addr1":"PLOT NO. G-3A, SECTOR-15, GIDA, Sahjanwa Road, Gorakhpur","Addr2":null,"Loc":"Gorakhpur","Pin":273209,"Stcd":"09","Ph":"9838755227"},"BuyerDtls":{"Gstin":"09CJFPM2579G1ZV","LglNm":"SHRI GANPATI ENTERPRISES","TrdNm":"SHRI GANPATI ENTERPRISES","Pos":"9","Addr1":"GUPTA GALI,MADHUBAN","Addr2":null,"Loc":"MAU","Pin":221603,"Stcd":"9","Ph":null},"DispDtls":{"Nm":"SHRI GANPATI ENTERPRISES","Addr1":"GUPTA GALI,MADHUBAN","Addr2":null,"Loc":"MAU","Pin":221603,"Stcd":"9"},"ShipDtls":{"Gstin":"09CJFPM2579G1ZV","LglNm":"SHRI GANPATI ENTERPRISES","TrdNm":"SHRI GANPATI ENTERPRISES","Addr1":"GUPTA GALI,MADHUBAN","Addr2":null,"Loc":"MAU","Pin":221603,"Stcd":"9"},"ValDtls":{"AssVal":96408,"IgstVal":0,"CgstVal":2410.2,"SgstVal":2410.2,"CesVal":0,"StCesVal":0,"Discount":0,"OthChrg":0,"RndOffAmt":-0.4,"TotInvVal":101228},"ExpDtls":{"ShipBNo":null,"ShipBDt":null,"Port":null,"RefClm":null,"ForCur":null,"CntCode":null,"ExpDuty":0},"EwbDtls":null,"ItemList":[{"SlNo":"1","PrdDesc":"210690","IsServc":"N","HsnCd":"210690","Barcde":null,"Qty":3600,"FreeQty":0,"Unit":"Pcs","UnitPrice":3.09,"TotAmt":11124,"Discount":0,"PreTaxVal":0,"AssAmt":11124,"GstRt":5,"IgstAmt":0,"CgstAmt":278.1,"SgstAmt":278.1,"CesRt":0,"CesAmt":0,"CesNonAdvlAmt":0,"StateCesRt":0,"StateCesAmt":0,"StateCesNonAdvlAmt":0,"OthChrg":0,"TotItemVal":11680.2,"BchDtls":null},{"SlNo":"2","PrdDesc":"210690","IsServc":"N","HsnCd":"210690","Barcde":null,"Qty":14400,"FreeQty":0,"Unit":"Pcs","UnitPrice":3.09,"TotAmt":44496,"Discount":0,"PreTaxVal":0,"AssAmt":44496,"GstRt":5,"IgstAmt":0,"CgstAmt":1112.4,"SgstAmt":1112.4,"CesRt":0,"CesAmt":0,"CesNonAdvlAmt":0,"StateCesRt":0,"StateCesAmt":0,"StateCesNonAdvlAmt":0,"OthChrg":0,"TotItemVal":46720.8,"BchDtls":null},{"SlNo":"3","PrdDesc":"210690","IsServc":"N","HsnCd":"210690","Barcde":null,"Qty":8400,"FreeQty":0,"Unit":"Pcs","UnitPrice":3.09,"TotAmt":25956,"Discount":0,"PreTaxVal":0,"AssAmt":25956,"GstRt":5,"IgstAmt":0,"CgstAmt":648.9,"SgstAmt":648.9,"CesRt":0,"CesAmt":0,"CesNonAdvlAmt":0,"StateCesRt":0,"StateCesAmt":0,"StateCesNonAdvlAmt":0,"OthChrg":0,"TotItemVal":27253.8,"BchDtls":null},{"SlNo":"4","PrdDesc":"210690","IsServc":"N","HsnCd":"210690","Barcde":null,"Qty":3600,"FreeQty":0,"Unit":"Pcs","UnitPrice":3.09,"TotAmt":11124,"Discount":0,"PreTaxVal":0,"AssAmt":11124,"GstRt":5,"IgstAmt":0,"CgstAmt":278.1,"SgstAmt":278.1,"CesRt":0,"CesAmt":0,"CesNonAdvlAmt":0,"StateCesRt":0,"StateCesAmt":0,"StateCesNonAdvlAmt":0,"OthChrg":0,"TotItemVal":11680.2,"BchDtls":null},{"SlNo":"5","PrdDesc":"210690","IsServc":"N","HsnCd":"210690","Barcde":null,"Qty":1200,"FreeQty":0,"Unit":"Pcs","UnitPrice":3.09,"TotAmt":3708,"Discount":0,"PreTaxVal":0,"AssAmt":3708,"GstRt":5,"IgstAmt":0,"CgstAmt":92.7,"SgstAmt":92.7,"CesRt":0,"CesAmt":0,"CesNonAdvlAmt":0,"StateCesRt":0,"StateCesAmt":0,"StateCesNonAdvlAmt":0,"OthChrg":0,"TotItemVal":3893.4,"BchDtls":null}]}]