[{"Version":"1.1","TranDtls":{"TaxSch":"GST","SupTyp":"B2B","IgstOnIntra":"N","RegRev":"N","EcmGstin":null},"DocDtls":{"Typ":"INV","No":"TAX22300112","Dt":"14\/04\/2022"},"SellerDtls":{"Gstin":"09AAMFC6710F2ZG","LglNm":"CRAZY BAKERY UDYOG","TrdNm":"CRAZY BAKERY UDYOG","Addr1":"PLOT NO. G-3A, SECTOR-15, GIDA, Sahjanwa Road, Gorakhpur","Addr2":null,"Loc":"Gorakhpur","Pin":273209,"Stcd":"09","Ph":"9838755227"},"BuyerDtls":{"Gstin":"06BNPPK5870B1ZW","LglNm":"KALKA JI ENTERPRISES","TrdNm":"KALKA JI ENTERPRISES","Pos":"6","Addr1":"H.NO - 7, WORD NO-26, NEAR MITTAL DOCTOR","Addr2":null,"Loc":"PALWAL","Pin":121102,"Stcd":"6","Ph":null},"DispDtls":{"Nm":"KALKA JI ENTERPRISES","Addr1":"H.NO - 7, WORD NO-26, NEAR MITTAL DOCTOR","Addr2":null,"Loc":"PALWAL","Pin":121102,"Stcd":"6"},"ShipDtls":{"Gstin":"06BNPPK5870B1ZW","LglNm":"KALKA JI ENTERPRISES","TrdNm":"KALKA JI ENTERPRISES","Addr1":"H.NO - 7, WORD NO-26, NEAR MITTAL DOCTOR","Addr2":null,"Loc":"PALWAL","Pin":121102,"Stcd":"6"},"ValDtls":{"AssVal":279316.8,"IgstVal":13965.84,"CgstVal":0,"SgstVal":0,"CesVal":0,"StCesVal":0,"Discount":0,"OthChrg":0,"RndOffAmt":0.36,"TotInvVal":293283},"ExpDtls":{"ShipBNo":null,"ShipBDt":null,"Port":null,"RefClm":null,"ForCur":null,"CntCode":null,"ExpDuty":0},"EwbDtls":null,"ItemList":[{"SlNo":"1","PrdDesc":"210690","IsServc":"N","HsnCd":"210690","Barcde":null,"Qty":25200,"FreeQty":0,"Unit":"Pcs","UnitPrice":3.26,"TotAmt":82152,"Discount":0,"PreTaxVal":0,"AssAmt":82152,"GstRt":5,"IgstAmt":4107.6,"CgstAmt":0,"SgstAmt":0,"CesRt":0,"CesAmt":0,"CesNonAdvlAmt":0,"StateCesRt":0,"StateCesAmt":0,"StateCesNonAdvlAmt":0,"OthChrg":0,"TotItemVal":86259.6,"BchDtls":null},{"SlNo":"2","PrdDesc":"210690","IsServc":"N","HsnCd":"210690","Barcde":null,"Qty":55440,"FreeQty":0,"Unit":"Pcs","UnitPrice":3.26,"TotAmt":180734.4,"Discount":0,"PreTaxVal":0,"AssAmt":180734.4,"GstRt":5,"IgstAmt":9036.72,"CgstAmt":0,"SgstAmt":0,"CesRt":0,"CesAmt":0,"CesNonAdvlAmt":0,"StateCesRt":0,"StateCesAmt":0,"StateCesNonAdvlAmt":0,"OthChrg":0,"TotItemVal":189771.12,"BchDtls":null},{"SlNo":"3","PrdDesc":"210690","IsServc":"N","HsnCd":"210690","Barcde":null,"Qty":3360,"FreeQty":0,"Unit":"Pcs","UnitPrice":3.26,"TotAmt":10953.6,"Discount":0,"PreTaxVal":0,"AssAmt":10953.6,"GstRt":5,"IgstAmt":547.68,"CgstAmt":0,"SgstAmt":0,"CesRt":0,"CesAmt":0,"CesNonAdvlAmt":0,"StateCesRt":0,"StateCesAmt":0,"StateCesNonAdvlAmt":0,"OthChrg":0,"TotItemVal":11501.28,"BchDtls":null},{"SlNo":"4","PrdDesc":"210690","IsServc":"N","HsnCd":"210690","Barcde":null,"Qty":1680,"FreeQty":0,"Unit":"Pcs","UnitPrice":3.26,"TotAmt":5476.8,"Discount":0,"PreTaxVal":0,"AssAmt":5476.8,"GstRt":5,"IgstAmt":273.84,"CgstAmt":0,"SgstAmt":0,"CesRt":0,"CesAmt":0,"CesNonAdvlAmt":0,"StateCesRt":0,"StateCesAmt":0,"StateCesNonAdvlAmt":0,"OthChrg":0,"TotItemVal":5750.64,"BchDtls":null}]}]